sum_50/__init__.py
sum_50-0.0.1.dist-info/METADATA
sum_50-0.0.1.dist-info/WHEEL
sum_50-0.0.1.dist-info/license.txt
sum_50-0.0.1.dist-info/top_level.txt
sum_50-0.0.1.dist-info/RECORD
